COPYING
COPYING.LESSER
MANIFEST.in
Makefile
README.rst
compile-niflheim.sh
depend.CHANGES
makefile-Darwin-x86_64
makefile-Linux-x86_64-gnu
makefile-Linux-x86_64-intel
makefile-Nifl7_broadwell_el8_foss
makefile-Nifl7_broadwell_el8_intel
makefile-Nifl7_epyc9004_foss
makefile-Nifl7_epyc9004_intel
makefile-Nifl7_icelake_foss
makefile-Nifl7_icelake_intel
makefile-Nifl7_nehalem_foss
makefile-Nifl7_nehalem_intel
makefile-Nifl7_sandybridge_foss
makefile-Nifl7_sandybridge_intel
makefile-Nifl7_skylake_el8_foss
makefile-Nifl7_skylake_el8_intel
makefile-Niflheim7
makefile-Niflheim7-gcc
makefile-Niflheim7-gcc-mkl
makefile-default
makefile-local
makefile-local-gcc-svml
recordversion.py
setup.py
Basics/Asap.h
Basics/AsapNamespace.h
Basics/AsapObject.cpp
Basics/AsapObject.h
Basics/AsapPython.h
Basics/Atoms.h
Basics/AtomsBasis.h
Basics/Debug.cpp
Basics/Debug.h
Basics/DynamicAtoms.cpp
Basics/DynamicAtoms.h
Basics/Exception.cpp
Basics/Exception.h
Basics/IVec.h
Basics/ImageAtoms.cpp
Basics/ImageAtoms.h
Basics/ImagePotential.cpp
Basics/ImagePotential.h
Basics/Langevin.cpp
Basics/Langevin.h
Basics/Matrix3x3.cpp
Basics/Matrix3x3.h
Basics/MolecularDynamics.cpp
Basics/MolecularDynamics.h
Basics/MonteCarloAtoms.cpp
Basics/MonteCarloAtoms.h
Basics/NeighborCellLocator.cpp
Basics/NeighborCellLocator.h
Basics/NeighborList.cpp
Basics/NeighborList.h
Basics/NeighborList2013.cpp
Basics/NeighborList2013.h
Basics/NeighborLocator.cpp
Basics/NeighborLocator.h
Basics/NormalAtoms.cpp
Basics/NormalAtoms.h
Basics/RandomNumbers.cpp
Basics/RandomNumbers.h
Basics/SymTensor.h
Basics/Timing.cpp
Basics/Timing.h
Basics/TimingResults.h
Basics/TinyMatrix.h
Basics/Vec.cpp
Basics/Vec.h
Basics/VelocityVerlet.cpp
Basics/VelocityVerlet.h
Basics/mass.h
Basics/stacktrace.c
Basics/stacktrace.h
Brenner/AtomPairInfoState.h
Brenner/BrennerPotential.cpp
Brenner/BrennerPotential.h
Brenner/asapbrenner.h
Brenner/bcuint.cpp
Brenner/caguts.cpp
Brenner/expand.cpp
Brenner/expand.h
Brenner/inter2d_iv.cpp
Brenner/mtable.cpp
asap3.egg-info/PKG-INFO
asap3.egg-info/SOURCES.txt
asap3.egg-info/dependency_links.txt
asap3.egg-info/requires.txt
asap3.egg-info/top_level.txt
