Metadata-Version: 2.2
Name: asap3
Version: 3.13.7
Summary: ASAP - classical potentials for MD with ASE.
Home-page: https://wiki.fysik.dtu.dk/asap
Maintainer: Jakob Schiotz et. al.
Maintainer-email: schiotz@fysik.dtu.dk
License: LGPLv3
Platform: unix
Classifier: Development Status :: 5 - Production/Stable
Classifier: License :: OSI Approved :: GNU Lesser General Public License v3 (LGPLv3)
Classifier: Operating System :: POSIX
Classifier: Operating System :: MacOS :: MacOS X
Classifier: Programming Language :: Python :: 3
Classifier: Programming Language :: Python :: 3.9
Classifier: Programming Language :: Python :: 3.10
Classifier: Programming Language :: Python :: 3.11
Classifier: Programming Language :: Python :: 3.12
Classifier: Programming Language :: Python :: 3.13
Classifier: Topic :: Scientific/Engineering :: Physics
License-File: COPYING
License-File: COPYING.LESSER
Requires-Dist: ase>=3.23.0
Dynamic: classifier
Dynamic: description
Dynamic: home-page
Dynamic: license
Dynamic: maintainer
Dynamic: maintainer-email
Dynamic: platform
Dynamic: requires-dist
Dynamic: summary
